[
  {
    "id": "b4ee16b5-734a-40e2-81ca-300a86b7536d",
    "club": "Sin club",
    "asociacion": "RIO BIO-BIO",
    "fecha": "2026-02-25",
    "tipo_rodeo_id": "457379a9-bf1f-446b-8b29-1c6a669a0f6d",
    "tipo_rodeo_nombre": "Clasificatorio Sur",
    "duracion_dias": 5,
    "observacion": null,
    "origen": "importado",
    "estado": "activo",
    "importacion_id": "c8b601f9-becd-4bbd-a406-88bc907b4c1e",
    "created_at": "2026-04-02T23:37:05.128319+00:00",
    "updated_at": "2026-04-02T23:37:05.128319+00:00",
    "created_by": "456ec336-9f82-452b-bee4-b6cb95d88982",
    "categoria_rodeo_id": null,
    "categoria_rodeo_nombre": null
  },
  {
    "id": "665d6f34-7207-4648-9b1d-f3741e33b0d9",
    "club": "YUNGAY",
    "asociacion": "ÑUBLE CORDILLERA",
    "fecha": "2026-02-22",
    "tipo_rodeo_id": "e22d954b-fab1-453b-97d3-b3d96db5e2d7",
    "tipo_rodeo_nombre": "Provincial Especial - Un Día",
    "duracion_dias": 1,
    "observacion": null,
    "origen": "importado",
    "estado": "activo",
    "importacion_id": "c8b601f9-becd-4bbd-a406-88bc907b4c1e",
    "created_at": "2026-04-02T23:37:05.658998+00:00",
    "updated_at": "2026-04-02T23:37:05.658998+00:00",
    "created_by": "456ec336-9f82-452b-bee4-b6cb95d88982",
    "categoria_rodeo_id": null,
    "categoria_rodeo_nombre": null
  },
  {
    "id": "3a1c5d96-fba3-48d5-bf9b-199eb83bbe7f",
    "club": "LA CELIA",
    "asociacion": "CUYO",
    "fecha": "2026-02-21",
    "tipo_rodeo_id": "d2c4383d-b266-4b80-beaf-f4f9dc857a8f",
    "tipo_rodeo_nombre": "Libre",
    "duracion_dias": 2,
    "observacion": null,
    "origen": "importado",
    "estado": "activo",
    "importacion_id": "c8b601f9-becd-4bbd-a406-88bc907b4c1e",
    "created_at": "2026-04-02T23:37:06.190669+00:00",
    "updated_at": "2026-04-02T23:37:06.190669+00:00",
    "created_by": "456ec336-9f82-452b-bee4-b6cb95d88982",
    "categoria_rodeo_id": null,
    "categoria_rodeo_nombre": null
  },
  {
    "id": "e3c23e07-3b5d-4444-a286-48ac56518ba4",
    "club": "CABRERO",
    "asociacion": "CONCEPCIÓN",
    "fecha": "2026-02-14",
    "tipo_rodeo_id": "a72449da-5163-45c3-b547-8897dd4e02da",
    "tipo_rodeo_nombre": "Provincial Especial Series Sexo",
    "duracion_dias": 2,
    "observacion": null,
    "origen": "importado",
    "estado": "activo",
    "importacion_id": "c8b601f9-becd-4bbd-a406-88bc907b4c1e",
    "created_at": "2026-04-02T23:37:06.722884+00:00",
    "updated_at": "2026-04-02T23:37:06.722884+00:00",
    "created_by": "456ec336-9f82-452b-bee4-b6cb95d88982",
    "categoria_rodeo_id": null,
    "categoria_rodeo_nombre": null
  },
  {
    "id": "ceb774d4-8b60-426c-98fe-7d785b1af7d0",
    "club": "PEDRO AGUIRRE CERDA",
    "asociacion": "SANTIAGO PONIENTE",
    "fecha": "2026-02-14",
    "tipo_rodeo_id": "863c4f37-8e1f-4011-b863-01b267cb922f",
    "tipo_rodeo_nombre": "Provincial - Un Día",
    "duracion_dias": 1,
    "observacion": null,
    "origen": "importado",
    "estado": "activo",
    "importacion_id": "c8b601f9-becd-4bbd-a406-88bc907b4c1e",
    "created_at": "2026-04-02T23:37:07.226541+00:00",
    "updated_at": "2026-04-02T23:37:07.226541+00:00",
    "created_by": "456ec336-9f82-452b-bee4-b6cb95d88982",
    "categoria_rodeo_id": null,
    "categoria_rodeo_nombre": null
  },
  {
    "id": "83732953-4a6b-4344-b7ac-2125576ef0fb",
    "club": "MANANTIALES DE PARRAL",
    "asociacion": "MAULE SUR",
    "fecha": "2026-02-14",
    "tipo_rodeo_id": "8ddb4da7-58e0-4f5a-bbe4-54cbe6b02131",
    "tipo_rodeo_nombre": "Provincial Especial Series Libres",
    "duracion_dias": 2,
    "observacion": null,
    "origen": "importado",
    "estado": "activo",
    "importacion_id": "c8b601f9-becd-4bbd-a406-88bc907b4c1e",
    "created_at": "2026-04-02T23:37:07.746632+00:00",
    "updated_at": "2026-04-02T23:37:07.746632+00:00",
    "created_by": "456ec336-9f82-452b-bee4-b6cb95d88982",
    "categoria_rodeo_id": null,
    "categoria_rodeo_nombre": null
  },
  {
    "id": "fe14697c-c96f-4564-b3d0-fe740a936a8c",
    "club": "RIO MAITENES DE MOLINA",
    "asociacion": "CURICÓ",
    "fecha": "2026-02-14",
    "tipo_rodeo_id": "863c4f37-8e1f-4011-b863-01b267cb922f",
    "tipo_rodeo_nombre": "Provincial - Un Día",
    "duracion_dias": 1,
    "observacion": null,
    "origen": "importado",
    "estado": "activo",
    "importacion_id": "c8b601f9-becd-4bbd-a406-88bc907b4c1e",
    "created_at": "2026-04-02T23:37:08.257378+00:00",
    "updated_at": "2026-04-02T23:37:08.257378+00:00",
    "created_by": "456ec336-9f82-452b-bee4-b6cb95d88982",
    "categoria_rodeo_id": null,
    "categoria_rodeo_nombre": null
  },
  {
    "id": "ef0d3331-2a87-4567-8dec-dbbca825fa7f",
    "club": "LITUECHE",
    "asociacion": "CARDENAL CARO",
    "fecha": "2026-02-14",
    "tipo_rodeo_id": "b619ea72-65dd-4a40-99c1-c26fe719aff6",
    "tipo_rodeo_nombre": "Interclubes Series Libres",
    "duracion_dias": 2,
    "observacion": null,
    "origen": "importado",
    "estado": "activo",
    "importacion_id": "c8b601f9-becd-4bbd-a406-88bc907b4c1e",
    "created_at": "2026-04-02T23:37:08.770306+00:00",
    "updated_at": "2026-04-02T23:37:08.770306+00:00",
    "created_by": "456ec336-9f82-452b-bee4-b6cb95d88982",
    "categoria_rodeo_id": null,
    "categoria_rodeo_nombre": null
  },
  {
    "id": "f532a272-9b0e-4dd7-b4cc-42714ef0fc4f",
    "club": "LAGO RANCO ALFONSO BRANDT",
    "asociacion": "VALDIVIA",
    "fecha": "2026-02-14",
    "tipo_rodeo_id": "8ddb4da7-58e0-4f5a-bbe4-54cbe6b02131",
    "tipo_rodeo_nombre": "Provincial Especial Series Libres",
    "duracion_dias": 2,
    "observacion": null,
    "origen": "importado",
    "estado": "activo",
    "importacion_id": "c8b601f9-becd-4bbd-a406-88bc907b4c1e",
    "created_at": "2026-04-02T23:37:09.277941+00:00",
    "updated_at": "2026-04-02T23:37:09.277941+00:00",
    "created_by": "456ec336-9f82-452b-bee4-b6cb95d88982",
    "categoria_rodeo_id": null,
    "categoria_rodeo_nombre": null
  },
  {
    "id": "4756bf44-9f01-4d41-a720-f4f71d682301",
    "club": "CLUB DE RODEO CHAITEN",
    "asociacion": "LAGO LLANQUIHUE",
    "fecha": "2026-02-14",
    "tipo_rodeo_id": "863c4f37-8e1f-4011-b863-01b267cb922f",
    "tipo_rodeo_nombre": "Provincial - Un Día",
    "duracion_dias": 1,
    "observacion": null,
    "origen": "importado",
    "estado": "activo",
    "importacion_id": "c8b601f9-becd-4bbd-a406-88bc907b4c1e",
    "created_at": "2026-04-02T23:37:09.787855+00:00",
    "updated_at": "2026-04-02T23:37:09.787855+00:00",
    "created_by": "456ec336-9f82-452b-bee4-b6cb95d88982",
    "categoria_rodeo_id": null,
    "categoria_rodeo_nombre": null
  },
  {
    "id": "ef9fc8c6-62dd-48e9-aa1b-dd44b0a1a13e",
    "club": "HUEMUL",
    "asociacion": "COLCHAGUA",
    "fecha": "2026-02-14",
    "tipo_rodeo_id": "c80a0bad-7b84-4670-94cb-fdd31e0739f8",
    "tipo_rodeo_nombre": "Provincial Series Libres",
    "duracion_dias": 2,
    "observacion": null,
    "origen": "importado",
    "estado": "activo",
    "importacion_id": "c8b601f9-becd-4bbd-a406-88bc907b4c1e",
    "created_at": "2026-04-02T23:37:10.296157+00:00",
    "updated_at": "2026-04-02T23:37:10.296157+00:00",
    "created_by": "456ec336-9f82-452b-bee4-b6cb95d88982",
    "categoria_rodeo_id": null,
    "categoria_rodeo_nombre": null
  },
  {
    "id": "a01e3877-dc1e-45b0-a907-90ff9bdd35c6",
    "club": "EL OLIVAR",
    "asociacion": "O'HIGGINS",
    "fecha": "2026-02-14",
    "tipo_rodeo_id": "e22d954b-fab1-453b-97d3-b3d96db5e2d7",
    "tipo_rodeo_nombre": "Provincial Especial - Un Día",
    "duracion_dias": 1,
    "observacion": null,
    "origen": "importado",
    "estado": "activo",
    "importacion_id": "c8b601f9-becd-4bbd-a406-88bc907b4c1e",
    "created_at": "2026-04-02T23:37:10.825449+00:00",
    "updated_at": "2026-04-02T23:37:10.825449+00:00",
    "created_by": "456ec336-9f82-452b-bee4-b6cb95d88982",
    "categoria_rodeo_id": null,
    "categoria_rodeo_nombre": null
  },
  {
    "id": "2763558d-e2b2-4c19-a408-330647cdfc52",
    "club": "CATO",
    "asociacion": "ÑUBLE CORDILLERA",
    "fecha": "2026-02-14",
    "tipo_rodeo_id": "c80a0bad-7b84-4670-94cb-fdd31e0739f8",
    "tipo_rodeo_nombre": "Provincial Series Libres",
    "duracion_dias": 2,
    "observacion": null,
    "origen": "importado",
    "estado": "activo",
    "importacion_id": "c8b601f9-becd-4bbd-a406-88bc907b4c1e",
    "created_at": "2026-04-02T23:37:11.337388+00:00",
    "updated_at": "2026-04-02T23:37:11.337388+00:00",
    "created_by": "456ec336-9f82-452b-bee4-b6cb95d88982",
    "categoria_rodeo_id": null,
    "categoria_rodeo_nombre": null
  },
  {
    "id": "674fba09-9e60-4c90-88ad-2280a6c210ba",
    "club": "GORBEA",
    "asociacion": "RÍO CAUTÍN",
    "fecha": "2026-02-14",
    "tipo_rodeo_id": "622dd0e6-51f5-454e-b942-8241a50a7f47",
    "tipo_rodeo_nombre": "Interasociaciones Especial Limitado a 25 Colleras",
    "duracion_dias": 2,
    "observacion": null,
    "origen": "importado",
    "estado": "activo",
    "importacion_id": "c8b601f9-becd-4bbd-a406-88bc907b4c1e",
    "created_at": "2026-04-02T23:37:11.894311+00:00",
    "updated_at": "2026-04-02T23:37:11.894311+00:00",
    "created_by": "456ec336-9f82-452b-bee4-b6cb95d88982",
    "categoria_rodeo_id": null,
    "categoria_rodeo_nombre": null
  },
  {
    "id": "ab48158a-76b7-491c-8a4d-c523809539c7",
    "club": "TORRES DEL PAINE",
    "asociacion": "MAGALLANES",
    "fecha": "2026-02-14",
    "tipo_rodeo_id": "8ddb4da7-58e0-4f5a-bbe4-54cbe6b02131",
    "tipo_rodeo_nombre": "Provincial Especial Series Libres",
    "duracion_dias": 2,
    "observacion": null,
    "origen": "importado",
    "estado": "activo",
    "importacion_id": "c8b601f9-becd-4bbd-a406-88bc907b4c1e",
    "created_at": "2026-04-02T23:37:12.407387+00:00",
    "updated_at": "2026-04-02T23:37:12.407387+00:00",
    "created_by": "456ec336-9f82-452b-bee4-b6cb95d88982",
    "categoria_rodeo_id": null,
    "categoria_rodeo_nombre": null
  },
  {
    "id": "5acee6d6-24ef-4d34-989b-f1d918db6c3f",
    "club": "CATAPILCO",
    "asociacion": "PETORCA",
    "fecha": "2026-02-14",
    "tipo_rodeo_id": "8ddb4da7-58e0-4f5a-bbe4-54cbe6b02131",
    "tipo_rodeo_nombre": "Provincial Especial Series Libres",
    "duracion_dias": 2,
    "observacion": null,
    "origen": "importado",
    "estado": "activo",
    "importacion_id": "c8b601f9-becd-4bbd-a406-88bc907b4c1e",
    "created_at": "2026-04-02T23:37:12.940387+00:00",
    "updated_at": "2026-04-02T23:37:12.940387+00:00",
    "created_by": "456ec336-9f82-452b-bee4-b6cb95d88982",
    "categoria_rodeo_id": null,
    "categoria_rodeo_nombre": null
  },
  {
    "id": "7cf5203f-8afc-4693-a06e-53d8025fefe1",
    "club": "VALLE DE ACUYO",
    "asociacion": "VALPARAÍSO",
    "fecha": "2026-02-14",
    "tipo_rodeo_id": "1b2abe24-e529-467b-9c55-e83d65c00e50",
    "tipo_rodeo_nombre": "Provincial 3 series Especial",
    "duracion_dias": 2,
    "observacion": null,
    "origen": "importado",
    "estado": "activo",
    "importacion_id": "c8b601f9-becd-4bbd-a406-88bc907b4c1e",
    "created_at": "2026-04-02T23:37:13.441121+00:00",
    "updated_at": "2026-04-02T23:37:13.441121+00:00",
    "created_by": "456ec336-9f82-452b-bee4-b6cb95d88982",
    "categoria_rodeo_id": null,
    "categoria_rodeo_nombre": null
  },
  {
    "id": "0d626eda-cd6c-42b5-945a-137a71f45e14",
    "club": "RANCAGUA",
    "asociacion": "RIO CACHAPOAL",
    "fecha": "2026-02-14",
    "tipo_rodeo_id": "1b2abe24-e529-467b-9c55-e83d65c00e50",
    "tipo_rodeo_nombre": "Provincial 3 series Especial",
    "duracion_dias": 2,
    "observacion": null,
    "origen": "importado",
    "estado": "activo",
    "importacion_id": "c8b601f9-becd-4bbd-a406-88bc907b4c1e",
    "created_at": "2026-04-02T23:37:13.965802+00:00",
    "updated_at": "2026-04-02T23:37:13.965802+00:00",
    "created_by": "456ec336-9f82-452b-bee4-b6cb95d88982",
    "categoria_rodeo_id": null,
    "categoria_rodeo_nombre": null
  },
  {
    "id": "646b6571-e4e2-420e-bf19-8392ef18a6eb",
    "club": "SANTA BARBARA",
    "asociacion": "RIO BIO-BIO",
    "fecha": "2026-02-14",
    "tipo_rodeo_id": "1b2abe24-e529-467b-9c55-e83d65c00e50",
    "tipo_rodeo_nombre": "Provincial 3 series Especial",
    "duracion_dias": 2,
    "observacion": null,
    "origen": "importado",
    "estado": "activo",
    "importacion_id": "c8b601f9-becd-4bbd-a406-88bc907b4c1e",
    "created_at": "2026-04-02T23:37:14.48359+00:00",
    "updated_at": "2026-04-02T23:37:14.48359+00:00",
    "created_by": "456ec336-9f82-452b-bee4-b6cb95d88982",
    "categoria_rodeo_id": null,
    "categoria_rodeo_nombre": null
  },
  {
    "id": "7efabc8d-6351-405e-a3f3-ac708af9b047",
    "club": "PELLUHUE - BARRIO ESTACION",
    "asociacion": "CAUQUENES",
    "fecha": "2026-02-14",
    "tipo_rodeo_id": "c80a0bad-7b84-4670-94cb-fdd31e0739f8",
    "tipo_rodeo_nombre": "Provincial Series Libres",
    "duracion_dias": 2,
    "observacion": null,
    "origen": "importado",
    "estado": "activo",
    "importacion_id": "c8b601f9-becd-4bbd-a406-88bc907b4c1e",
    "created_at": "2026-04-02T23:37:15.006707+00:00",
    "updated_at": "2026-04-02T23:37:15.006707+00:00",
    "created_by": "456ec336-9f82-452b-bee4-b6cb95d88982",
    "categoria_rodeo_id": null,
    "categoria_rodeo_nombre": null
  },
  {
    "id": "90fe9ccb-68c2-4cca-aced-b3628f0805ec",
    "club": "CHILLAN",
    "asociacion": "ÑUBLE",
    "fecha": "2026-02-14",
    "tipo_rodeo_id": "622dd0e6-51f5-454e-b942-8241a50a7f47",
    "tipo_rodeo_nombre": "Interasociaciones Especial Limitado a 25 Colleras",
    "duracion_dias": 2,
    "observacion": null,
    "origen": "importado",
    "estado": "activo",
    "importacion_id": "c8b601f9-becd-4bbd-a406-88bc907b4c1e",
    "created_at": "2026-04-02T23:37:15.540509+00:00",
    "updated_at": "2026-04-02T23:37:15.540509+00:00",
    "created_by": "456ec336-9f82-452b-bee4-b6cb95d88982",
    "categoria_rodeo_id": null,
    "categoria_rodeo_nombre": null
  },
  {
    "id": "cfecc54f-d897-4541-9663-66a4ed78eade",
    "club": "LA JUNTA",
    "asociacion": "AYSÉN",
    "fecha": "2026-02-14",
    "tipo_rodeo_id": "d2c4383d-b266-4b80-beaf-f4f9dc857a8f",
    "tipo_rodeo_nombre": "Libre",
    "duracion_dias": 2,
    "observacion": null,
    "origen": "importado",
    "estado": "activo",
    "importacion_id": "c8b601f9-becd-4bbd-a406-88bc907b4c1e",
    "created_at": "2026-04-02T23:37:16.071252+00:00",
    "updated_at": "2026-04-02T23:37:16.071252+00:00",
    "created_by": "456ec336-9f82-452b-bee4-b6cb95d88982",
    "categoria_rodeo_id": null,
    "categoria_rodeo_nombre": null
  },
  {
    "id": "f5311568-2198-435b-9ad0-58479f6c316b",
    "club": "PEDRO AGUIRRE CERDA DE CALLE LARGA",
    "asociacion": "LOS ANDES",
    "fecha": "2026-02-14",
    "tipo_rodeo_id": "5016c2d3-a1dc-4a88-a469-4ee71de7fa11",
    "tipo_rodeo_nombre": "Provincial 3 series",
    "duracion_dias": 2,
    "observacion": null,
    "origen": "importado",
    "estado": "activo",
    "importacion_id": "c8b601f9-becd-4bbd-a406-88bc907b4c1e",
    "created_at": "2026-04-02T23:37:16.58866+00:00",
    "updated_at": "2026-04-02T23:37:16.58866+00:00",
    "created_by": "456ec336-9f82-452b-bee4-b6cb95d88982",
    "categoria_rodeo_id": null,
    "categoria_rodeo_nombre": null
  },
  {
    "id": "b167d214-ec01-4e95-95dd-aefcd0185bfe",
    "club": "CURACAUTIN",
    "asociacion": "MALLECO",
    "fecha": "2026-02-14",
    "tipo_rodeo_id": "fa71c138-86e1-4e82-a51a-85e0df11de6b",
    "tipo_rodeo_nombre": "Interasociaciones Limitado 25 colleras",
    "duracion_dias": 2,
    "observacion": null,
    "origen": "importado",
    "estado": "activo",
    "importacion_id": "c8b601f9-becd-4bbd-a406-88bc907b4c1e",
    "created_at": "2026-04-02T23:37:17.106974+00:00",
    "updated_at": "2026-04-02T23:37:17.106974+00:00",
    "created_by": "456ec336-9f82-452b-bee4-b6cb95d88982",
    "categoria_rodeo_id": null,
    "categoria_rodeo_nombre": null
  },
  {
    "id": "da7effea-cf78-4026-9f00-a1c9a02d30a8",
    "club": "TINAJON",
    "asociacion": "BÍO-BÍO",
    "fecha": "2026-02-14",
    "tipo_rodeo_id": "863c4f37-8e1f-4011-b863-01b267cb922f",
    "tipo_rodeo_nombre": "Provincial - Un Día",
    "duracion_dias": 1,
    "observacion": null,
    "origen": "importado",
    "estado": "activo",
    "importacion_id": "c8b601f9-becd-4bbd-a406-88bc907b4c1e",
    "created_at": "2026-04-02T23:37:17.643676+00:00",
    "updated_at": "2026-04-02T23:37:17.643676+00:00",
    "created_by": "456ec336-9f82-452b-bee4-b6cb95d88982",
    "categoria_rodeo_id": null,
    "categoria_rodeo_nombre": null
  },
  {
    "id": "dcafe7e7-316a-48e2-b4c3-c67e55c6ae8b",
    "club": "RIO CHOAPA",
    "asociacion": "CHOAPA",
    "fecha": "2026-02-14",
    "tipo_rodeo_id": "8ddb4da7-58e0-4f5a-bbe4-54cbe6b02131",
    "tipo_rodeo_nombre": "Provincial Especial Series Libres",
    "duracion_dias": 2,
    "observacion": null,
    "origen": "importado",
    "estado": "activo",
    "importacion_id": "c8b601f9-becd-4bbd-a406-88bc907b4c1e",
    "created_at": "2026-04-02T23:37:18.174928+00:00",
    "updated_at": "2026-04-02T23:37:18.174928+00:00",
    "created_by": "456ec336-9f82-452b-bee4-b6cb95d88982",
    "categoria_rodeo_id": null,
    "categoria_rodeo_nombre": null
  },
  {
    "id": "567c6184-f7bb-4a43-b5a0-95f91f056c67",
    "club": "MARIA PINTO",
    "asociacion": "MELIPILLA",
    "fecha": "2026-02-14",
    "tipo_rodeo_id": "863c4f37-8e1f-4011-b863-01b267cb922f",
    "tipo_rodeo_nombre": "Provincial - Un Día",
    "duracion_dias": 1,
    "observacion": null,
    "origen": "importado",
    "estado": "activo",
    "importacion_id": "c8b601f9-becd-4bbd-a406-88bc907b4c1e",
    "created_at": "2026-04-02T23:37:18.698682+00:00",
    "updated_at": "2026-04-02T23:37:18.698682+00:00",
    "created_by": "456ec336-9f82-452b-bee4-b6cb95d88982",
    "categoria_rodeo_id": null,
    "categoria_rodeo_nombre": null
  },
  {
    "id": "720e4d2f-ee9d-417f-9797-d0841020a289",
    "club": "SAN VICENTE DE TAGUA-TAGUA",
    "asociacion": "EL LIBERTADOR",
    "fecha": "2026-02-14",
    "tipo_rodeo_id": "1b2abe24-e529-467b-9c55-e83d65c00e50",
    "tipo_rodeo_nombre": "Provincial 3 series Especial",
    "duracion_dias": 2,
    "observacion": null,
    "origen": "importado",
    "estado": "activo",
    "importacion_id": "c8b601f9-becd-4bbd-a406-88bc907b4c1e",
    "created_at": "2026-04-02T23:37:19.244293+00:00",
    "updated_at": "2026-04-02T23:37:19.244293+00:00",
    "created_by": "456ec336-9f82-452b-bee4-b6cb95d88982",
    "categoria_rodeo_id": null,
    "categoria_rodeo_nombre": null
  },
  {
    "id": "07914ed9-356b-42ce-8546-21a25b6bf3b2",
    "club": "CRUCERO PURRANQUE",
    "asociacion": "RIO RAHUE",
    "fecha": "2026-02-14",
    "tipo_rodeo_id": "e22d954b-fab1-453b-97d3-b3d96db5e2d7",
    "tipo_rodeo_nombre": "Provincial Especial - Un Día",
    "duracion_dias": 1,
    "observacion": null,
    "origen": "importado",
    "estado": "activo",
    "importacion_id": "c8b601f9-becd-4bbd-a406-88bc907b4c1e",
    "created_at": "2026-04-02T23:37:19.76251+00:00",
    "updated_at": "2026-04-02T23:37:19.76251+00:00",
    "created_by": "456ec336-9f82-452b-bee4-b6cb95d88982",
    "categoria_rodeo_id": null,
    "categoria_rodeo_nombre": null
  },
  {
    "id": "d6b6551b-c384-4a9e-b51d-1eebafd4e01c",
    "club": "ANCUD",
    "asociacion": "CHILOE",
    "fecha": "2026-02-14",
    "tipo_rodeo_id": "1b2abe24-e529-467b-9c55-e83d65c00e50",
    "tipo_rodeo_nombre": "Provincial 3 series Especial",
    "duracion_dias": 2,
    "observacion": null,
    "origen": "importado",
    "estado": "activo",
    "importacion_id": "c8b601f9-becd-4bbd-a406-88bc907b4c1e",
    "created_at": "2026-04-02T23:37:20.306212+00:00",
    "updated_at": "2026-04-02T23:37:20.306212+00:00",
    "created_by": "456ec336-9f82-452b-bee4-b6cb95d88982",
    "categoria_rodeo_id": null,
    "categoria_rodeo_nombre": null
  },
  {
    "id": "cf73d9e9-576b-41d4-82b9-14a3292cb442",
    "club": "PALENA",
    "asociacion": "LAGO LLANQUIHUE",
    "fecha": "2026-02-08",
    "tipo_rodeo_id": "863c4f37-8e1f-4011-b863-01b267cb922f",
    "tipo_rodeo_nombre": "Provincial - Un Día",
    "duracion_dias": 1,
    "observacion": null,
    "origen": "importado",
    "estado": "activo",
    "importacion_id": "c8b601f9-becd-4bbd-a406-88bc907b4c1e",
    "created_at": "2026-04-02T23:37:20.833561+00:00",
    "updated_at": "2026-04-02T23:37:20.833561+00:00",
    "created_by": "456ec336-9f82-452b-bee4-b6cb95d88982",
    "categoria_rodeo_id": null,
    "categoria_rodeo_nombre": null
  },
  {
    "id": "7117db56-df1a-414e-92d3-1cf854b85624",
    "club": "HUEPIL",
    "asociacion": "RIO BIO-BIO",
    "fecha": "2026-02-08",
    "tipo_rodeo_id": "e22d954b-fab1-453b-97d3-b3d96db5e2d7",
    "tipo_rodeo_nombre": "Provincial Especial - Un Día",
    "duracion_dias": 1,
    "observacion": null,
    "origen": "importado",
    "estado": "activo",
    "importacion_id": "c8b601f9-becd-4bbd-a406-88bc907b4c1e",
    "created_at": "2026-04-02T23:37:21.359871+00:00",
    "updated_at": "2026-04-02T23:37:21.359871+00:00",
    "created_by": "456ec336-9f82-452b-bee4-b6cb95d88982",
    "categoria_rodeo_id": null,
    "categoria_rodeo_nombre": null
  },
  {
    "id": "ba846526-54dd-4172-837c-0fad055dcf19",
    "club": "QUILLOTA",
    "asociacion": "QUILLOTA",
    "fecha": "2026-02-07",
    "tipo_rodeo_id": "c80a0bad-7b84-4670-94cb-fdd31e0739f8",
    "tipo_rodeo_nombre": "Provincial Series Libres",
    "duracion_dias": 2,
    "observacion": null,
    "origen": "importado",
    "estado": "activo",
    "importacion_id": "c8b601f9-becd-4bbd-a406-88bc907b4c1e",
    "created_at": "2026-04-02T23:37:21.88155+00:00",
    "updated_at": "2026-04-02T23:37:21.88155+00:00",
    "created_by": "456ec336-9f82-452b-bee4-b6cb95d88982",
    "categoria_rodeo_id": null,
    "categoria_rodeo_nombre": null
  },
  {
    "id": "82ca31d9-10eb-4bc5-88b9-3b205aba1e42",
    "club": "PUERTO CISNES",
    "asociacion": "AYSÉN",
    "fecha": "2026-02-07",
    "tipo_rodeo_id": "d2c4383d-b266-4b80-beaf-f4f9dc857a8f",
    "tipo_rodeo_nombre": "Libre",
    "duracion_dias": 2,
    "observacion": null,
    "origen": "importado",
    "estado": "activo",
    "importacion_id": "c8b601f9-becd-4bbd-a406-88bc907b4c1e",
    "created_at": "2026-04-02T23:37:22.415664+00:00",
    "updated_at": "2026-04-02T23:37:22.415664+00:00",
    "created_by": "456ec336-9f82-452b-bee4-b6cb95d88982",
    "categoria_rodeo_id": null,
    "categoria_rodeo_nombre": null
  },
  {
    "id": "baee4994-9c1d-4dff-bf7c-bf198f969637",
    "club": "SAN IGNACIO",
    "asociacion": "ÑUBLE",
    "fecha": "2026-02-07",
    "tipo_rodeo_id": "5016c2d3-a1dc-4a88-a469-4ee71de7fa11",
    "tipo_rodeo_nombre": "Provincial 3 series",
    "duracion_dias": 2,
    "observacion": null,
    "origen": "importado",
    "estado": "activo",
    "importacion_id": "c8b601f9-becd-4bbd-a406-88bc907b4c1e",
    "created_at": "2026-04-02T23:37:22.923858+00:00",
    "updated_at": "2026-04-02T23:37:22.923858+00:00",
    "created_by": "456ec336-9f82-452b-bee4-b6cb95d88982",
    "categoria_rodeo_id": null,
    "categoria_rodeo_nombre": null
  },
  {
    "id": "de9bb2f1-7614-4aa4-9872-e9aef8a414eb",
    "club": "HUALPIN",
    "asociacion": "RÍO CAUTÍN",
    "fecha": "2026-02-07",
    "tipo_rodeo_id": "c80a0bad-7b84-4670-94cb-fdd31e0739f8",
    "tipo_rodeo_nombre": "Provincial Series Libres",
    "duracion_dias": 2,
    "observacion": null,
    "origen": "importado",
    "estado": "activo",
    "importacion_id": "c8b601f9-becd-4bbd-a406-88bc907b4c1e",
    "created_at": "2026-04-02T23:37:23.462808+00:00",
    "updated_at": "2026-04-02T23:37:23.462808+00:00",
    "created_by": "456ec336-9f82-452b-bee4-b6cb95d88982",
    "categoria_rodeo_id": null,
    "categoria_rodeo_nombre": null
  },
  {
    "id": "b87a9f78-2564-4804-835e-18e83fa6393b",
    "club": "LUMACO",
    "asociacion": "MALLECO",
    "fecha": "2026-02-07",
    "tipo_rodeo_id": "5016c2d3-a1dc-4a88-a469-4ee71de7fa11",
    "tipo_rodeo_nombre": "Provincial 3 series",
    "duracion_dias": 2,
    "observacion": null,
    "origen": "importado",
    "estado": "activo",
    "importacion_id": "c8b601f9-becd-4bbd-a406-88bc907b4c1e",
    "created_at": "2026-04-02T23:37:24.016111+00:00",
    "updated_at": "2026-04-02T23:37:24.016111+00:00",
    "created_by": "456ec336-9f82-452b-bee4-b6cb95d88982",
    "categoria_rodeo_id": null,
    "categoria_rodeo_nombre": null
  },
  {
    "id": "59cfaffb-0d9d-4f72-81de-6f67407e08aa",
    "club": "LO PRADO",
    "asociacion": "SANTIAGO PONIENTE",
    "fecha": "2026-02-07",
    "tipo_rodeo_id": "863c4f37-8e1f-4011-b863-01b267cb922f",
    "tipo_rodeo_nombre": "Provincial - Un Día",
    "duracion_dias": 1,
    "observacion": null,
    "origen": "importado",
    "estado": "activo",
    "importacion_id": "c8b601f9-becd-4bbd-a406-88bc907b4c1e",
    "created_at": "2026-04-02T23:37:24.566928+00:00",
    "updated_at": "2026-04-02T23:37:24.566928+00:00",
    "created_by": "456ec336-9f82-452b-bee4-b6cb95d88982",
    "categoria_rodeo_id": null,
    "categoria_rodeo_nombre": null
  },
  {
    "id": "72a7a9e5-cd74-4918-8691-7a865e1ccccd",
    "club": "CHEPICA",
    "asociacion": "VALLE SANTA CRUZ",
    "fecha": "2026-02-07",
    "tipo_rodeo_id": "863c4f37-8e1f-4011-b863-01b267cb922f",
    "tipo_rodeo_nombre": "Provincial - Un Día",
    "duracion_dias": 1,
    "observacion": null,
    "origen": "importado",
    "estado": "activo",
    "importacion_id": "c8b601f9-becd-4bbd-a406-88bc907b4c1e",
    "created_at": "2026-04-02T23:37:25.08999+00:00",
    "updated_at": "2026-04-02T23:37:25.08999+00:00",
    "created_by": "456ec336-9f82-452b-bee4-b6cb95d88982",
    "categoria_rodeo_id": null,
    "categoria_rodeo_nombre": null
  },
  {
    "id": "e68119a6-95a6-42d7-be0e-47e565b46912",
    "club": "PAREDONES",
    "asociacion": "CARDENAL CARO",
    "fecha": "2026-02-07",
    "tipo_rodeo_id": "b05d6311-56e1-4672-8712-18a82f7d6d97",
    "tipo_rodeo_nombre": "Interclubes 3 series",
    "duracion_dias": 2,
    "observacion": null,
    "origen": "importado",
    "estado": "activo",
    "importacion_id": "c8b601f9-becd-4bbd-a406-88bc907b4c1e",
    "created_at": "2026-04-02T23:37:25.660177+00:00",
    "updated_at": "2026-04-02T23:37:25.660177+00:00",
    "created_by": "456ec336-9f82-452b-bee4-b6cb95d88982",
    "categoria_rodeo_id": null,
    "categoria_rodeo_nombre": null
  },
  {
    "id": "233d7e30-5dda-4e2e-b0e8-0b1c9a818644",
    "club": "POBLACÍON",
    "asociacion": "COLCHAGUA",
    "fecha": "2026-02-07",
    "tipo_rodeo_id": "5016c2d3-a1dc-4a88-a469-4ee71de7fa11",
    "tipo_rodeo_nombre": "Provincial 3 series",
    "duracion_dias": 2,
    "observacion": null,
    "origen": "importado",
    "estado": "activo",
    "importacion_id": "c8b601f9-becd-4bbd-a406-88bc907b4c1e",
    "created_at": "2026-04-02T23:37:26.175282+00:00",
    "updated_at": "2026-04-02T23:37:26.175282+00:00",
    "created_by": "456ec336-9f82-452b-bee4-b6cb95d88982",
    "categoria_rodeo_id": null,
    "categoria_rodeo_nombre": null
  },
  {
    "id": "57e4e0a0-beda-4f19-8a4a-6cbb617deec4",
    "club": "RELONCAVI",
    "asociacion": "LLANQUIHUE",
    "fecha": "2026-02-07",
    "tipo_rodeo_id": "863c4f37-8e1f-4011-b863-01b267cb922f",
    "tipo_rodeo_nombre": "Provincial - Un Día",
    "duracion_dias": 1,
    "observacion": null,
    "origen": "importado",
    "estado": "activo",
    "importacion_id": "c8b601f9-becd-4bbd-a406-88bc907b4c1e",
    "created_at": "2026-04-02T23:37:27.282383+00:00",
    "updated_at": "2026-04-02T23:37:27.282383+00:00",
    "created_by": "456ec336-9f82-452b-bee4-b6cb95d88982",
    "categoria_rodeo_id": null,
    "categoria_rodeo_nombre": null
  },
  {
    "id": "a35d78af-6382-4da0-85ee-1e168e782b83",
    "club": "FUTRONO",
    "asociacion": "VALDIVIA",
    "fecha": "2026-02-07",
    "tipo_rodeo_id": "5016c2d3-a1dc-4a88-a469-4ee71de7fa11",
    "tipo_rodeo_nombre": "Provincial 3 series",
    "duracion_dias": 2,
    "observacion": null,
    "origen": "importado",
    "estado": "activo",
    "importacion_id": "c8b601f9-becd-4bbd-a406-88bc907b4c1e",
    "created_at": "2026-04-02T23:37:28.299233+00:00",
    "updated_at": "2026-04-02T23:37:28.299233+00:00",
    "created_by": "456ec336-9f82-452b-bee4-b6cb95d88982",
    "categoria_rodeo_id": null,
    "categoria_rodeo_nombre": null
  },
  {
    "id": "4ea2689c-3143-409b-91c8-59da5f4c0258",
    "club": "QUILLECO",
    "asociacion": "BÍO-BÍO",
    "fecha": "2026-02-07",
    "tipo_rodeo_id": "1b2abe24-e529-467b-9c55-e83d65c00e50",
    "tipo_rodeo_nombre": "Provincial 3 series Especial",
    "duracion_dias": 2,
    "observacion": null,
    "origen": "importado",
    "estado": "activo",
    "importacion_id": "c8b601f9-becd-4bbd-a406-88bc907b4c1e",
    "created_at": "2026-04-02T23:37:29.374315+00:00",
    "updated_at": "2026-04-02T23:37:29.374315+00:00",
    "created_by": "456ec336-9f82-452b-bee4-b6cb95d88982",
    "categoria_rodeo_id": null,
    "categoria_rodeo_nombre": null
  },
  {
    "id": "b6b86034-2210-4e79-9939-7f8cd6b0e586",
    "club": "NOCHACO PUERTO OCTAY",
    "asociacion": "RIO RAHUE",
    "fecha": "2026-02-07",
    "tipo_rodeo_id": "1b2abe24-e529-467b-9c55-e83d65c00e50",
    "tipo_rodeo_nombre": "Provincial 3 series Especial",
    "duracion_dias": 2,
    "observacion": null,
    "origen": "importado",
    "estado": "activo",
    "importacion_id": "c8b601f9-becd-4bbd-a406-88bc907b4c1e",
    "created_at": "2026-04-02T23:37:30.477514+00:00",
    "updated_at": "2026-04-02T23:37:30.477514+00:00",
    "created_by": "456ec336-9f82-452b-bee4-b6cb95d88982",
    "categoria_rodeo_id": null,
    "categoria_rodeo_nombre": null
  },
  {
    "id": "34a6a7b2-1845-427e-b7f1-db5a514c809c",
    "club": "PEDRO AGUIRRE CERDA DE CALLE LARGA",
    "asociacion": "LOS ANDES",
    "fecha": "2026-02-07",
    "tipo_rodeo_id": "5016c2d3-a1dc-4a88-a469-4ee71de7fa11",
    "tipo_rodeo_nombre": "Provincial 3 series",
    "duracion_dias": 2,
    "observacion": null,
    "origen": "importado",
    "estado": "activo",
    "importacion_id": "c8b601f9-becd-4bbd-a406-88bc907b4c1e",
    "created_at": "2026-04-02T23:37:31.537566+00:00",
    "updated_at": "2026-04-02T23:37:31.537566+00:00",
    "created_by": "456ec336-9f82-452b-bee4-b6cb95d88982",
    "categoria_rodeo_id": null,
    "categoria_rodeo_nombre": null
  },
  {
    "id": "63094894-ce8b-48ea-bc53-01e91668bfb4",
    "club": "GRANEROS",
    "asociacion": "EL LIBERTADOR",
    "fecha": "2026-02-07",
    "tipo_rodeo_id": "b05d6311-56e1-4672-8712-18a82f7d6d97",
    "tipo_rodeo_nombre": "Interclubes 3 series",
    "duracion_dias": 2,
    "observacion": null,
    "origen": "importado",
    "estado": "activo",
    "importacion_id": "c8b601f9-becd-4bbd-a406-88bc907b4c1e",
    "created_at": "2026-04-02T23:37:32.575196+00:00",
    "updated_at": "2026-04-02T23:37:32.575196+00:00",
    "created_by": "456ec336-9f82-452b-bee4-b6cb95d88982",
    "categoria_rodeo_id": null,
    "categoria_rodeo_nombre": null
  },
  {
    "id": "abdd0d8d-9521-4643-86b0-b6cda9584233",
    "club": "SAN PABLO",
    "asociacion": "OSORNO",
    "fecha": "2026-02-07",
    "tipo_rodeo_id": "5016c2d3-a1dc-4a88-a469-4ee71de7fa11",
    "tipo_rodeo_nombre": "Provincial 3 series",
    "duracion_dias": 2,
    "observacion": null,
    "origen": "importado",
    "estado": "activo",
    "importacion_id": "c8b601f9-becd-4bbd-a406-88bc907b4c1e",
    "created_at": "2026-04-02T23:37:33.619754+00:00",
    "updated_at": "2026-04-02T23:37:33.619754+00:00",
    "created_by": "456ec336-9f82-452b-bee4-b6cb95d88982",
    "categoria_rodeo_id": null,
    "categoria_rodeo_nombre": null
  },
  {
    "id": "c5460922-b617-4e87-9dea-788316ca23a6",
    "club": "NANCAGUA",
    "asociacion": "VALLE SANTA CRUZ",
    "fecha": "2026-02-01",
    "tipo_rodeo_id": "863c4f37-8e1f-4011-b863-01b267cb922f",
    "tipo_rodeo_nombre": "Provincial - Un Día",
    "duracion_dias": 1,
    "observacion": null,
    "origen": "importado",
    "estado": "activo",
    "importacion_id": "c8b601f9-becd-4bbd-a406-88bc907b4c1e",
    "created_at": "2026-04-02T23:37:34.732281+00:00",
    "updated_at": "2026-04-02T23:37:34.732281+00:00",
    "created_by": "456ec336-9f82-452b-bee4-b6cb95d88982",
    "categoria_rodeo_id": null,
    "categoria_rodeo_nombre": null
  },
  {
    "id": "0e1fe36e-4ccf-4d91-a6f5-0b896746bdd8",
    "club": "FUTALEUFU",
    "asociacion": "LAGO LLANQUIHUE",
    "fecha": "2026-02-07",
    "tipo_rodeo_id": "d2c4383d-b266-4b80-beaf-f4f9dc857a8f",
    "tipo_rodeo_nombre": "Libre",
    "duracion_dias": 2,
    "observacion": null,
    "origen": "importado",
    "estado": "activo",
    "importacion_id": "c8b601f9-becd-4bbd-a406-88bc907b4c1e",
    "created_at": "2026-04-02T23:37:26.761414+00:00",
    "updated_at": "2026-04-02T23:37:26.761414+00:00",
    "created_by": "456ec336-9f82-452b-bee4-b6cb95d88982",
    "categoria_rodeo_id": null,
    "categoria_rodeo_nombre": null
  },
  {
    "id": "f14660fc-5ff5-41a1-a0f4-02e26b14fb4b",
    "club": "ARAUCO RURAL DE LEBU",
    "asociacion": "ARAUCO",
    "fecha": "2026-02-07",
    "tipo_rodeo_id": "b05d6311-56e1-4672-8712-18a82f7d6d97",
    "tipo_rodeo_nombre": "Interclubes 3 series",
    "duracion_dias": 2,
    "observacion": null,
    "origen": "importado",
    "estado": "activo",
    "importacion_id": "c8b601f9-becd-4bbd-a406-88bc907b4c1e",
    "created_at": "2026-04-02T23:37:27.79824+00:00",
    "updated_at": "2026-04-02T23:37:27.79824+00:00",
    "created_by": "456ec336-9f82-452b-bee4-b6cb95d88982",
    "categoria_rodeo_id": null,
    "categoria_rodeo_nombre": null
  },
  {
    "id": "fe054f76-6ee6-4aa7-83c6-d5a1d4aeae46",
    "club": "CALERA DE TANGO",
    "asociacion": "MAIPO NORTE",
    "fecha": "2026-02-07",
    "tipo_rodeo_id": "e22d954b-fab1-453b-97d3-b3d96db5e2d7",
    "tipo_rodeo_nombre": "Provincial Especial - Un Día",
    "duracion_dias": 1,
    "observacion": null,
    "origen": "importado",
    "estado": "activo",
    "importacion_id": "c8b601f9-becd-4bbd-a406-88bc907b4c1e",
    "created_at": "2026-04-02T23:37:28.853244+00:00",
    "updated_at": "2026-04-02T23:37:28.853244+00:00",
    "created_by": "456ec336-9f82-452b-bee4-b6cb95d88982",
    "categoria_rodeo_id": null,
    "categoria_rodeo_nombre": null
  },
  {
    "id": "03011c88-0ee9-4cf5-8b16-a6452070a323",
    "club": "PITRUFQUEN",
    "asociacion": "CAUTÍN",
    "fecha": "2026-02-07",
    "tipo_rodeo_id": "863c4f37-8e1f-4011-b863-01b267cb922f",
    "tipo_rodeo_nombre": "Provincial - Un Día",
    "duracion_dias": 1,
    "observacion": null,
    "origen": "importado",
    "estado": "activo",
    "importacion_id": "c8b601f9-becd-4bbd-a406-88bc907b4c1e",
    "created_at": "2026-04-02T23:37:29.95226+00:00",
    "updated_at": "2026-04-02T23:37:29.95226+00:00",
    "created_by": "456ec336-9f82-452b-bee4-b6cb95d88982",
    "categoria_rodeo_id": null,
    "categoria_rodeo_nombre": null
  },
  {
    "id": "495c9a06-b46d-4bba-96c6-dcfe7efac781",
    "club": "MOLINA",
    "asociacion": "AGUANEGRA",
    "fecha": "2026-02-07",
    "tipo_rodeo_id": "863c4f37-8e1f-4011-b863-01b267cb922f",
    "tipo_rodeo_nombre": "Provincial - Un Día",
    "duracion_dias": 1,
    "observacion": null,
    "origen": "importado",
    "estado": "activo",
    "importacion_id": "c8b601f9-becd-4bbd-a406-88bc907b4c1e",
    "created_at": "2026-04-02T23:37:31.006582+00:00",
    "updated_at": "2026-04-02T23:37:31.006582+00:00",
    "created_by": "456ec336-9f82-452b-bee4-b6cb95d88982",
    "categoria_rodeo_id": null,
    "categoria_rodeo_nombre": null
  },
  {
    "id": "59278f7e-df58-4542-b804-64a520e68721",
    "club": "PUERTO NATALES",
    "asociacion": "MAGALLANES",
    "fecha": "2026-02-07",
    "tipo_rodeo_id": "5016c2d3-a1dc-4a88-a469-4ee71de7fa11",
    "tipo_rodeo_nombre": "Provincial 3 series",
    "duracion_dias": 2,
    "observacion": null,
    "origen": "importado",
    "estado": "activo",
    "importacion_id": "c8b601f9-becd-4bbd-a406-88bc907b4c1e",
    "created_at": "2026-04-02T23:37:32.063056+00:00",
    "updated_at": "2026-04-02T23:37:32.063056+00:00",
    "created_by": "456ec336-9f82-452b-bee4-b6cb95d88982",
    "categoria_rodeo_id": null,
    "categoria_rodeo_nombre": null
  },
  {
    "id": "690eb19c-c685-4354-91fe-cad949852ac0",
    "club": "DALCAHUE",
    "asociacion": "CHILOE",
    "fecha": "2026-02-07",
    "tipo_rodeo_id": "1b2abe24-e529-467b-9c55-e83d65c00e50",
    "tipo_rodeo_nombre": "Provincial 3 series Especial",
    "duracion_dias": 2,
    "observacion": null,
    "origen": "importado",
    "estado": "activo",
    "importacion_id": "c8b601f9-becd-4bbd-a406-88bc907b4c1e",
    "created_at": "2026-04-02T23:37:33.092282+00:00",
    "updated_at": "2026-04-02T23:37:33.092282+00:00",
    "created_by": "456ec336-9f82-452b-bee4-b6cb95d88982",
    "categoria_rodeo_id": null,
    "categoria_rodeo_nombre": null
  },
  {
    "id": "4e0bb2ea-a2fb-448e-8d8e-77bb38ee6432",
    "club": "CHINCOLCO",
    "asociacion": "PETORCA",
    "fecha": "2026-02-07",
    "tipo_rodeo_id": "8ddb4da7-58e0-4f5a-bbe4-54cbe6b02131",
    "tipo_rodeo_nombre": "Provincial Especial Series Libres",
    "duracion_dias": 2,
    "observacion": null,
    "origen": "importado",
    "estado": "activo",
    "importacion_id": "c8b601f9-becd-4bbd-a406-88bc907b4c1e",
    "created_at": "2026-04-02T23:37:34.193965+00:00",
    "updated_at": "2026-04-02T23:37:34.193965+00:00",
    "created_by": "456ec336-9f82-452b-bee4-b6cb95d88982",
    "categoria_rodeo_id": null,
    "categoria_rodeo_nombre": null
  },
  {
    "id": "e97eaf89-fbde-449e-9641-3f537c3e6953",
    "club": "",
    "asociacion": "",
    "fecha": "2026-02-14",
    "tipo_rodeo_id": "5016c2d3-a1dc-4a88-a469-4ee71de7fa11",
    "tipo_rodeo_nombre": "Provincial 3 series",
    "duracion_dias": 2,
    "observacion": null,
    "origen": "importado",
    "estado": "activo",
    "importacion_id": "c8b601f9-becd-4bbd-a406-88bc907b4c1e",
    "created_at": "2026-04-02T23:52:01.917429+00:00",
    "updated_at": "2026-04-02T23:52:01.917429+00:00",
    "created_by": "456ec336-9f82-452b-bee4-b6cb95d88982",
    "categoria_rodeo_id": null,
    "categoria_rodeo_nombre": null
  },
  {
    "id": "90bd02ee-b77d-4a50-8a71-c9a3e586b51e",
    "club": "LOS MUERMOS",
    "asociacion": "LAGO LLANQUIHUE",
    "fecha": "2026-03-21",
    "tipo_rodeo_id": "d2c4383d-b266-4b80-beaf-f4f9dc857a8f",
    "tipo_rodeo_nombre": "Libre",
    "duracion_dias": 2,
    "observacion": null,
    "origen": "importado",
    "estado": "activo",
    "importacion_id": "b8921efa-49d7-457d-aaa3-d15c874d52c4",
    "created_at": "2026-04-03T13:16:07.156404+00:00",
    "updated_at": "2026-04-03T13:16:07.156404+00:00",
    "created_by": "456ec336-9f82-452b-bee4-b6cb95d88982",
    "categoria_rodeo_id": null,
    "categoria_rodeo_nombre": null
  },
  {
    "id": "e7bce3c9-8642-48e3-9bca-23190e3c6101",
    "club": "Sin club",
    "asociacion": "MELIPILLA",
    "fecha": "2026-03-11",
    "tipo_rodeo_id": "03ad82d2-9369-470f-afa8-b4610b7db4c4",
    "tipo_rodeo_nombre": "Clasificatorio Norte",
    "duracion_dias": 5,
    "observacion": null,
    "origen": "importado",
    "estado": "activo",
    "importacion_id": "b8921efa-49d7-457d-aaa3-d15c874d52c4",
    "created_at": "2026-04-03T13:16:07.31261+00:00",
    "updated_at": "2026-04-03T13:16:07.31261+00:00",
    "created_by": "456ec336-9f82-452b-bee4-b6cb95d88982",
    "categoria_rodeo_id": null,
    "categoria_rodeo_nombre": null
  },
  {
    "id": "0e84d65c-3081-47a9-86bb-bd0e4eb0e883",
    "club": "Sin club",
    "asociacion": "TALCA",
    "fecha": "2026-03-04",
    "tipo_rodeo_id": "e58a2f0c-218f-4100-81fa-696440aa3693",
    "tipo_rodeo_nombre": "Clasificatorio Centro",
    "duracion_dias": 5,
    "observacion": null,
    "origen": "importado",
    "estado": "activo",
    "importacion_id": "b8921efa-49d7-457d-aaa3-d15c874d52c4",
    "created_at": "2026-04-03T13:16:07.470827+00:00",
    "updated_at": "2026-04-03T13:16:07.470827+00:00",
    "created_by": "456ec336-9f82-452b-bee4-b6cb95d88982",
    "categoria_rodeo_id": null,
    "categoria_rodeo_nombre": null
  },
  {
    "id": "01988a9a-5556-47be-bebf-86b53ce2237f",
    "club": "SAN JUAN DE LA COSTA",
    "asociacion": "OSORNO",
    "fecha": "2026-04-11",
    "tipo_rodeo_id": "5016c2d3-a1dc-4a88-a469-4ee71de7fa11",
    "tipo_rodeo_nombre": "Provincial 3 series",
    "duracion_dias": 2,
    "observacion": null,
    "origen": "importado",
    "estado": "activo",
    "importacion_id": "c3219bc4-2b2f-478b-98df-9d34dd620df4",
    "created_at": "2026-04-06T14:02:56.136598+00:00",
    "updated_at": "2026-04-06T14:02:56.136598+00:00",
    "created_by": "456ec336-9f82-452b-bee4-b6cb95d88982",
    "categoria_rodeo_id": null,
    "categoria_rodeo_nombre": null
  },
  {
    "id": "e03c9a77-a1e9-4662-b0d8-18fcabddfdbc",
    "club": "LAS CANTERAS DE O´HIGGINS",
    "asociacion": "BÍO-BÍO",
    "fecha": "2026-04-11",
    "tipo_rodeo_id": "5016c2d3-a1dc-4a88-a469-4ee71de7fa11",
    "tipo_rodeo_nombre": "Provincial 3 series",
    "duracion_dias": 2,
    "observacion": null,
    "origen": "importado",
    "estado": "activo",
    "importacion_id": "c3219bc4-2b2f-478b-98df-9d34dd620df4",
    "created_at": "2026-04-06T14:02:56.62032+00:00",
    "updated_at": "2026-04-06T14:02:56.62032+00:00",
    "created_by": "456ec336-9f82-452b-bee4-b6cb95d88982",
    "categoria_rodeo_id": null,
    "categoria_rodeo_nombre": null
  },
  {
    "id": "4677a695-e8f5-4350-b133-906c33b9d4bb",
    "club": "Los Castaños de Santa Ana",
    "asociacion": "CONCEPCIÓN",
    "fecha": "2026-04-11",
    "tipo_rodeo_id": "fa71c138-86e1-4e82-a51a-85e0df11de6b",
    "tipo_rodeo_nombre": "Interasociaciones Limitado 25 colleras",
    "duracion_dias": 2,
    "observacion": null,
    "origen": "importado",
    "estado": "activo",
    "importacion_id": "c3219bc4-2b2f-478b-98df-9d34dd620df4",
    "created_at": "2026-04-06T14:02:56.737801+00:00",
    "updated_at": "2026-04-06T14:02:56.737801+00:00",
    "created_by": "456ec336-9f82-452b-bee4-b6cb95d88982",
    "categoria_rodeo_id": null,
    "categoria_rodeo_nombre": null
  },
  {
    "id": "b8523447-5d31-4e7f-ad97-7f62fda68727",
    "club": "SAN ALBERTO",
    "asociacion": "TALAGANTE",
    "fecha": "2026-04-11",
    "tipo_rodeo_id": "1b2abe24-e529-467b-9c55-e83d65c00e50",
    "tipo_rodeo_nombre": "Provincial 3 series Especial",
    "duracion_dias": 2,
    "observacion": null,
    "origen": "importado",
    "estado": "activo",
    "importacion_id": "c3219bc4-2b2f-478b-98df-9d34dd620df4",
    "created_at": "2026-04-06T14:02:56.850774+00:00",
    "updated_at": "2026-04-06T14:02:56.850774+00:00",
    "created_by": "456ec336-9f82-452b-bee4-b6cb95d88982",
    "categoria_rodeo_id": null,
    "categoria_rodeo_nombre": null
  },
  {
    "id": "33ef6188-92ac-4ef5-b7fb-a55bd383fb21",
    "club": "PELLUHUE - BARRIO ESTACION",
    "asociacion": "CAUQUENES",
    "fecha": "2026-04-11",
    "tipo_rodeo_id": "c80a0bad-7b84-4670-94cb-fdd31e0739f8",
    "tipo_rodeo_nombre": "Provincial Series Libres",
    "duracion_dias": 2,
    "observacion": null,
    "origen": "importado",
    "estado": "activo",
    "importacion_id": "c3219bc4-2b2f-478b-98df-9d34dd620df4",
    "created_at": "2026-04-06T14:02:56.965445+00:00",
    "updated_at": "2026-04-06T14:02:56.965445+00:00",
    "created_by": "456ec336-9f82-452b-bee4-b6cb95d88982",
    "categoria_rodeo_id": null,
    "categoria_rodeo_nombre": null
  },
  {
    "id": "2ea642c0-6934-44ab-af95-3a9e4e1ec524",
    "club": "LOS LLANOS DE PELARCO",
    "asociacion": "TALCA ORIENTE",
    "fecha": "2026-04-11",
    "tipo_rodeo_id": "1b2abe24-e529-467b-9c55-e83d65c00e50",
    "tipo_rodeo_nombre": "Provincial 3 series Especial",
    "duracion_dias": 2,
    "observacion": null,
    "origen": "importado",
    "estado": "activo",
    "importacion_id": "c3219bc4-2b2f-478b-98df-9d34dd620df4",
    "created_at": "2026-04-06T14:02:57.089489+00:00",
    "updated_at": "2026-04-06T14:02:57.089489+00:00",
    "created_by": "456ec336-9f82-452b-bee4-b6cb95d88982",
    "categoria_rodeo_id": null,
    "categoria_rodeo_nombre": null
  },
  {
    "id": "507e6211-913c-46fe-b003-beaa0403cc61",
    "club": "FUTALEUFU",
    "asociacion": "LAGO LLANQUIHUE",
    "fecha": "2026-04-11",
    "tipo_rodeo_id": "d2c4383d-b266-4b80-beaf-f4f9dc857a8f",
    "tipo_rodeo_nombre": "Libre",
    "duracion_dias": 2,
    "observacion": null,
    "origen": "importado",
    "estado": "activo",
    "importacion_id": "c3219bc4-2b2f-478b-98df-9d34dd620df4",
    "created_at": "2026-04-06T14:02:57.20639+00:00",
    "updated_at": "2026-04-06T14:02:57.20639+00:00",
    "created_by": "456ec336-9f82-452b-bee4-b6cb95d88982",
    "categoria_rodeo_id": null,
    "categoria_rodeo_nombre": null
  },
  {
    "id": "c4ccc025-a45b-46ed-82ac-03c2aac565fd",
    "club": "ARAUCO RURAL DE LEBU",
    "asociacion": "ARAUCO",
    "fecha": "2026-04-11",
    "tipo_rodeo_id": "863c4f37-8e1f-4011-b863-01b267cb922f",
    "tipo_rodeo_nombre": "Provincial - Un Día",
    "duracion_dias": 1,
    "observacion": null,
    "origen": "importado",
    "estado": "activo",
    "importacion_id": "c3219bc4-2b2f-478b-98df-9d34dd620df4",
    "created_at": "2026-04-06T14:02:57.322714+00:00",
    "updated_at": "2026-04-06T14:02:57.322714+00:00",
    "created_by": "456ec336-9f82-452b-bee4-b6cb95d88982",
    "categoria_rodeo_id": null,
    "categoria_rodeo_nombre": null
  },
  {
    "id": "88fd2f16-cccc-423d-a659-b72b786ed4ae",
    "club": "SAN RAMON",
    "asociacion": "SANTIAGO SUR",
    "fecha": "2026-04-11",
    "tipo_rodeo_id": "5016c2d3-a1dc-4a88-a469-4ee71de7fa11",
    "tipo_rodeo_nombre": "Provincial 3 series",
    "duracion_dias": 2,
    "observacion": null,
    "origen": "importado",
    "estado": "activo",
    "importacion_id": "c3219bc4-2b2f-478b-98df-9d34dd620df4",
    "created_at": "2026-04-06T14:02:57.44048+00:00",
    "updated_at": "2026-04-06T14:02:57.44048+00:00",
    "created_by": "456ec336-9f82-452b-bee4-b6cb95d88982",
    "categoria_rodeo_id": null,
    "categoria_rodeo_nombre": null
  },
  {
    "id": "7e6d7b81-07c7-4847-affe-6212fa8bd1dc",
    "club": "REQUINOA",
    "asociacion": "EL LIBERTADOR",
    "fecha": "2026-04-11",
    "tipo_rodeo_id": "2db18356-3fec-4a38-ab3a-7e13e6114e3a",
    "tipo_rodeo_nombre": "Interclubes 3 series Especial",
    "duracion_dias": 2,
    "observacion": null,
    "origen": "importado",
    "estado": "activo",
    "importacion_id": "c3219bc4-2b2f-478b-98df-9d34dd620df4",
    "created_at": "2026-04-06T14:02:57.55478+00:00",
    "updated_at": "2026-04-06T14:02:57.55478+00:00",
    "created_by": "456ec336-9f82-452b-bee4-b6cb95d88982",
    "categoria_rodeo_id": null,
    "categoria_rodeo_nombre": null
  },
  {
    "id": "bad55de6-e095-4781-a6ef-72b06055e307",
    "club": "RANCAGUA",
    "asociacion": "RIO CACHAPOAL",
    "fecha": "2026-04-11",
    "tipo_rodeo_id": "1b2abe24-e529-467b-9c55-e83d65c00e50",
    "tipo_rodeo_nombre": "Provincial 3 series Especial",
    "duracion_dias": 2,
    "observacion": null,
    "origen": "importado",
    "estado": "activo",
    "importacion_id": "c3219bc4-2b2f-478b-98df-9d34dd620df4",
    "created_at": "2026-04-06T14:02:57.672444+00:00",
    "updated_at": "2026-04-06T14:02:57.672444+00:00",
    "created_by": "456ec336-9f82-452b-bee4-b6cb95d88982",
    "categoria_rodeo_id": null,
    "categoria_rodeo_nombre": null
  },
  {
    "id": "2c1fccdb-b7f1-4f70-b31e-826b1d517809",
    "club": "CORDILLERA RIO MAIPO",
    "asociacion": "CORDILLERA",
    "fecha": "2026-04-11",
    "tipo_rodeo_id": "863c4f37-8e1f-4011-b863-01b267cb922f",
    "tipo_rodeo_nombre": "Provincial - Un Día",
    "duracion_dias": 1,
    "observacion": null,
    "origen": "importado",
    "estado": "activo",
    "importacion_id": "c3219bc4-2b2f-478b-98df-9d34dd620df4",
    "created_at": "2026-04-06T14:02:57.780701+00:00",
    "updated_at": "2026-04-06T14:02:57.780701+00:00",
    "created_by": "456ec336-9f82-452b-bee4-b6cb95d88982",
    "categoria_rodeo_id": null,
    "categoria_rodeo_nombre": null
  },
  {
    "id": "582f1b16-9bcc-492e-aa38-0769910f228e",
    "club": "CATEMU",
    "asociacion": "SAN FELIPE",
    "fecha": "2026-04-11",
    "tipo_rodeo_id": "8ddb4da7-58e0-4f5a-bbe4-54cbe6b02131",
    "tipo_rodeo_nombre": "Provincial Especial Series Libres",
    "duracion_dias": 2,
    "observacion": null,
    "origen": "importado",
    "estado": "activo",
    "importacion_id": "c3219bc4-2b2f-478b-98df-9d34dd620df4",
    "created_at": "2026-04-06T14:02:57.889027+00:00",
    "updated_at": "2026-04-06T14:02:57.889027+00:00",
    "created_by": "456ec336-9f82-452b-bee4-b6cb95d88982",
    "categoria_rodeo_id": null,
    "categoria_rodeo_nombre": null
  },
  {
    "id": "802b93e2-7bc5-418b-9fd0-18e3030bd5a3",
    "club": "LO PRADO",
    "asociacion": "SANTIAGO PONIENTE",
    "fecha": "2026-04-11",
    "tipo_rodeo_id": "5016c2d3-a1dc-4a88-a469-4ee71de7fa11",
    "tipo_rodeo_nombre": "Provincial 3 series",
    "duracion_dias": 2,
    "observacion": null,
    "origen": "importado",
    "estado": "activo",
    "importacion_id": "c3219bc4-2b2f-478b-98df-9d34dd620df4",
    "created_at": "2026-04-06T14:02:57.999521+00:00",
    "updated_at": "2026-04-06T14:02:57.999521+00:00",
    "created_by": "456ec336-9f82-452b-bee4-b6cb95d88982",
    "categoria_rodeo_id": null,
    "categoria_rodeo_nombre": null
  },
  {
    "id": "673f2656-67b6-467c-8334-738a52f01077",
    "club": "SALAMANCA",
    "asociacion": "CHOAPA",
    "fecha": "2026-04-03",
    "tipo_rodeo_id": "e346dfb5-559b-480b-bc31-653679525998",
    "tipo_rodeo_nombre": "Interasociaciones",
    "duracion_dias": 2,
    "observacion": null,
    "origen": "importado",
    "estado": "activo",
    "importacion_id": "c3219bc4-2b2f-478b-98df-9d34dd620df4",
    "created_at": "2026-04-06T14:02:58.110481+00:00",
    "updated_at": "2026-04-06T14:02:58.110481+00:00",
    "created_by": "456ec336-9f82-452b-bee4-b6cb95d88982",
    "categoria_rodeo_id": null,
    "categoria_rodeo_nombre": null
  },
  {
    "id": "19db67fe-ebfc-4688-b4cc-bc0c23a94945",
    "club": "MANANTIALES DE PARRAL",
    "asociacion": "MAULE SUR",
    "fecha": "2026-04-18",
    "tipo_rodeo_id": "622dd0e6-51f5-454e-b942-8241a50a7f47",
    "tipo_rodeo_nombre": "Interasociaciones Especial Limitado a 25 Colleras",
    "duracion_dias": 2,
    "observacion": null,
    "origen": "importado",
    "estado": "activo",
    "importacion_id": "069461a2-bf44-4bc6-8968-b0e8bc731d93",
    "created_at": "2026-04-13T19:17:40.715027+00:00",
    "updated_at": "2026-04-13T19:17:40.715027+00:00",
    "created_by": "456ec336-9f82-452b-bee4-b6cb95d88982",
    "categoria_rodeo_id": null,
    "categoria_rodeo_nombre": null
  },
  {
    "id": "501c1d96-c47d-4885-8a62-16a023781e2b",
    "club": "HUEPIL",
    "asociacion": "RIO BIO-BIO",
    "fecha": "2026-04-18",
    "tipo_rodeo_id": "1b2abe24-e529-467b-9c55-e83d65c00e50",
    "tipo_rodeo_nombre": "Provincial 3 series Especial",
    "duracion_dias": 2,
    "observacion": null,
    "origen": "importado",
    "estado": "activo",
    "importacion_id": "069461a2-bf44-4bc6-8968-b0e8bc731d93",
    "created_at": "2026-04-13T19:17:40.846589+00:00",
    "updated_at": "2026-04-13T19:17:40.846589+00:00",
    "created_by": "456ec336-9f82-452b-bee4-b6cb95d88982",
    "categoria_rodeo_id": null,
    "categoria_rodeo_nombre": null
  },
  {
    "id": "4070b55d-55d9-4963-be01-6dd2e84b1d39",
    "club": "FERIAGRO",
    "asociacion": "CUYO",
    "fecha": "2026-04-18",
    "tipo_rodeo_id": "d2c4383d-b266-4b80-beaf-f4f9dc857a8f",
    "tipo_rodeo_nombre": "Libre",
    "duracion_dias": 2,
    "observacion": null,
    "origen": "importado",
    "estado": "activo",
    "importacion_id": "069461a2-bf44-4bc6-8968-b0e8bc731d93",
    "created_at": "2026-04-13T19:17:40.975888+00:00",
    "updated_at": "2026-04-13T19:17:40.975888+00:00",
    "created_by": "456ec336-9f82-452b-bee4-b6cb95d88982",
    "categoria_rodeo_id": null,
    "categoria_rodeo_nombre": null
  },
  {
    "id": "774b3ea1-6214-4c01-b022-b9353b9eb046",
    "club": "LOLOL",
    "asociacion": "VALLE SANTA CRUZ",
    "fecha": "2026-04-18",
    "tipo_rodeo_id": "863c4f37-8e1f-4011-b863-01b267cb922f",
    "tipo_rodeo_nombre": "Provincial - Un Día",
    "duracion_dias": 1,
    "observacion": null,
    "origen": "importado",
    "estado": "activo",
    "importacion_id": "069461a2-bf44-4bc6-8968-b0e8bc731d93",
    "created_at": "2026-04-13T19:17:41.122645+00:00",
    "updated_at": "2026-04-13T19:17:41.122645+00:00",
    "created_by": "456ec336-9f82-452b-bee4-b6cb95d88982",
    "categoria_rodeo_id": null,
    "categoria_rodeo_nombre": null
  },
  {
    "id": "f3a0b759-d9a7-4baa-8018-db069d089476",
    "club": "CHACABUCO",
    "asociacion": "CHACABUCO",
    "fecha": "2026-04-18",
    "tipo_rodeo_id": "1b2abe24-e529-467b-9c55-e83d65c00e50",
    "tipo_rodeo_nombre": "Provincial 3 series Especial",
    "duracion_dias": 2,
    "observacion": null,
    "origen": "importado",
    "estado": "activo",
    "importacion_id": "069461a2-bf44-4bc6-8968-b0e8bc731d93",
    "created_at": "2026-04-13T19:17:41.249361+00:00",
    "updated_at": "2026-04-13T19:17:41.249361+00:00",
    "created_by": "456ec336-9f82-452b-bee4-b6cb95d88982",
    "categoria_rodeo_id": null,
    "categoria_rodeo_nombre": null
  },
  {
    "id": "481c1a10-cf45-4263-a890-e686e02277c4",
    "club": "CUMPEO",
    "asociacion": "TALCA ORIENTE",
    "fecha": "2026-04-18",
    "tipo_rodeo_id": "1b2abe24-e529-467b-9c55-e83d65c00e50",
    "tipo_rodeo_nombre": "Provincial 3 series Especial",
    "duracion_dias": 2,
    "observacion": null,
    "origen": "importado",
    "estado": "activo",
    "importacion_id": "069461a2-bf44-4bc6-8968-b0e8bc731d93",
    "created_at": "2026-04-13T19:17:41.374222+00:00",
    "updated_at": "2026-04-13T19:17:41.374222+00:00",
    "created_by": "456ec336-9f82-452b-bee4-b6cb95d88982",
    "categoria_rodeo_id": null,
    "categoria_rodeo_nombre": null
  },
  {
    "id": "dca09d9e-9cbe-40c3-97d1-c095863e4926",
    "club": "GIL LETELIER",
    "asociacion": "SANTIAGO",
    "fecha": "2026-04-18",
    "tipo_rodeo_id": "1b2abe24-e529-467b-9c55-e83d65c00e50",
    "tipo_rodeo_nombre": "Provincial 3 series Especial",
    "duracion_dias": 2,
    "observacion": null,
    "origen": "importado",
    "estado": "activo",
    "importacion_id": "069461a2-bf44-4bc6-8968-b0e8bc731d93",
    "created_at": "2026-04-13T19:17:41.497445+00:00",
    "updated_at": "2026-04-13T19:17:41.497445+00:00",
    "created_by": "456ec336-9f82-452b-bee4-b6cb95d88982",
    "categoria_rodeo_id": null,
    "categoria_rodeo_nombre": null
  },
  {
    "id": "f12fbe68-3150-4c45-924d-ae8fc1d539fb",
    "club": "OSORNO - CANCURA",
    "asociacion": "OSORNO",
    "fecha": "2026-04-18",
    "tipo_rodeo_id": "5e0e3c74-ce3a-48e0-848a-f687a98c5860",
    "tipo_rodeo_nombre": "Interasociaciones Especial",
    "duracion_dias": 2,
    "observacion": null,
    "origen": "importado",
    "estado": "activo",
    "importacion_id": "069461a2-bf44-4bc6-8968-b0e8bc731d93",
    "created_at": "2026-04-13T19:17:41.617606+00:00",
    "updated_at": "2026-04-13T19:17:41.617606+00:00",
    "created_by": "456ec336-9f82-452b-bee4-b6cb95d88982",
    "categoria_rodeo_id": null,
    "categoria_rodeo_nombre": null
  },
  {
    "id": "8ae01a81-c111-4463-81bc-d5b7f74aba19",
    "club": "PAIHUEN",
    "asociacion": "PETORCA",
    "fecha": "2026-04-18",
    "tipo_rodeo_id": "8ddb4da7-58e0-4f5a-bbe4-54cbe6b02131",
    "tipo_rodeo_nombre": "Provincial Especial Series Libres",
    "duracion_dias": 2,
    "observacion": null,
    "origen": "importado",
    "estado": "activo",
    "importacion_id": "069461a2-bf44-4bc6-8968-b0e8bc731d93",
    "created_at": "2026-04-13T19:17:41.775703+00:00",
    "updated_at": "2026-04-13T19:17:41.775703+00:00",
    "created_by": "456ec336-9f82-452b-bee4-b6cb95d88982",
    "categoria_rodeo_id": null,
    "categoria_rodeo_nombre": null
  },
  {
    "id": "0cf55b2f-0100-42dd-980b-763472ef39e7",
    "club": "ALHUE",
    "asociacion": "MELIPILLA",
    "fecha": "2026-04-18",
    "tipo_rodeo_id": "5016c2d3-a1dc-4a88-a469-4ee71de7fa11",
    "tipo_rodeo_nombre": "Provincial 3 series",
    "duracion_dias": 2,
    "observacion": null,
    "origen": "importado",
    "estado": "activo",
    "importacion_id": "069461a2-bf44-4bc6-8968-b0e8bc731d93",
    "created_at": "2026-04-13T19:17:41.894423+00:00",
    "updated_at": "2026-04-13T19:17:41.894423+00:00",
    "created_by": "456ec336-9f82-452b-bee4-b6cb95d88982",
    "categoria_rodeo_id": null,
    "categoria_rodeo_nombre": null
  },
  {
    "id": "518b8883-d206-4839-b455-2cc8fe73b0bd",
    "club": "YERBAS BUENAS",
    "asociacion": "LINARES",
    "fecha": "2026-04-18",
    "tipo_rodeo_id": "5016c2d3-a1dc-4a88-a469-4ee71de7fa11",
    "tipo_rodeo_nombre": "Provincial 3 series",
    "duracion_dias": 2,
    "observacion": null,
    "origen": "importado",
    "estado": "activo",
    "importacion_id": "069461a2-bf44-4bc6-8968-b0e8bc731d93",
    "created_at": "2026-04-13T19:17:42.013761+00:00",
    "updated_at": "2026-04-13T19:17:42.013761+00:00",
    "created_by": "456ec336-9f82-452b-bee4-b6cb95d88982",
    "categoria_rodeo_id": null,
    "categoria_rodeo_nombre": null
  },
  {
    "id": "4e0e7c69-78e2-4aea-be34-98b51bfd1894",
    "club": "Casablanca Litoral",
    "asociacion": "LITORAL CENTRAL",
    "fecha": "2026-04-18",
    "tipo_rodeo_id": "5016c2d3-a1dc-4a88-a469-4ee71de7fa11",
    "tipo_rodeo_nombre": "Provincial 3 series",
    "duracion_dias": 2,
    "observacion": null,
    "origen": "importado",
    "estado": "activo",
    "importacion_id": "069461a2-bf44-4bc6-8968-b0e8bc731d93",
    "created_at": "2026-04-13T19:17:42.129631+00:00",
    "updated_at": "2026-04-13T19:17:42.129631+00:00",
    "created_by": "456ec336-9f82-452b-bee4-b6cb95d88982",
    "categoria_rodeo_id": null,
    "categoria_rodeo_nombre": null
  },
  {
    "id": "aa8b64a3-ffa1-4bda-8a85-4a077caeb398",
    "club": "VIÑA DEL MAR",
    "asociacion": "VALPARAÍSO",
    "fecha": "2026-04-18",
    "tipo_rodeo_id": "1b2abe24-e529-467b-9c55-e83d65c00e50",
    "tipo_rodeo_nombre": "Provincial 3 series Especial",
    "duracion_dias": 2,
    "observacion": null,
    "origen": "importado",
    "estado": "activo",
    "importacion_id": "069461a2-bf44-4bc6-8968-b0e8bc731d93",
    "created_at": "2026-04-13T19:17:42.250903+00:00",
    "updated_at": "2026-04-13T19:17:42.250903+00:00",
    "created_by": "456ec336-9f82-452b-bee4-b6cb95d88982",
    "categoria_rodeo_id": null,
    "categoria_rodeo_nombre": null
  },
  {
    "id": "1cf51a38-bd1d-4425-99c5-47b09b494115",
    "club": "Sin club",
    "asociacion": "AGUANEGRA",
    "fecha": "2026-04-17",
    "tipo_rodeo_id": "3ec53f79-6207-4f44-af31-b764d45aceaf",
    "tipo_rodeo_nombre": "Rodeo Nacional Universitario",
    "duracion_dias": 3,
    "observacion": null,
    "origen": "importado",
    "estado": "activo",
    "importacion_id": "069461a2-bf44-4bc6-8968-b0e8bc731d93",
    "created_at": "2026-04-13T19:17:42.371057+00:00",
    "updated_at": "2026-04-13T19:17:42.371057+00:00",
    "created_by": "456ec336-9f82-452b-bee4-b6cb95d88982",
    "categoria_rodeo_id": null,
    "categoria_rodeo_nombre": null
  },
  {
    "id": "494bceff-cece-40ab-902d-152b47141268",
    "club": "MANANTIALES DE PARRAL",
    "asociacion": "MAULE SUR",
    "fecha": "2026-04-25",
    "tipo_rodeo_id": "622dd0e6-51f5-454e-b942-8241a50a7f47",
    "tipo_rodeo_nombre": "Interasociaciones Especial Limitado a 25 Colleras",
    "duracion_dias": 2,
    "observacion": null,
    "origen": "importado",
    "estado": "activo",
    "importacion_id": "7f0f7c4e-9521-4386-9ba7-bc07a82f9d56",
    "created_at": "2026-04-13T20:17:57.202823+00:00",
    "updated_at": "2026-04-13T20:17:57.202823+00:00",
    "created_by": "456ec336-9f82-452b-bee4-b6cb95d88982",
    "categoria_rodeo_id": null,
    "categoria_rodeo_nombre": null
  }
]